[
    {
        "question": "Qué año llegó Cristóbal Colón a América?",
        "answer":"1492"
    },
    {
        "question": "En qué año comenzó la II Guerra Mundial?",
        "answer":"1939"
    },
    {
        "question": "Qué son los humanos: omnívoros, herbívoros o carnívoros?",
        "answer":"Omnívoros"
    },
    {
        "question": "Cuántas patas tiene la araña?",
        "answer":"8"
    },
    {
        "question": "Quién ganó el mundial de 2014?",
        "answer":"Alemania"
    },
    {
        "question": "Quién traicionó a Jesús?",
        "answer":"Judas"
    },
    {
        "question": "Cuántos años tiene un lustro?",
        "answer":"5"
    },
    {
        "question": "Cuál es el monte más alto del mundo?",
        "answer":"Everest"
    },
    {
        "question": "Quién fue el famoso cantante del grupo musical Queen?",
        "answer":"Freddie Mercury"
    },
    {
        "question": "Quién escribió la Ilíada y la Odisea?",
        "answer":"Homero"
    },
    {
        "question": "Quién pintó el “Guernica”?",
        "answer":"Pablo Picasso"
    },
    {
        "question": "Alrededor de qué planeta orbitan los satélites Ganímedes, Calisto, Ío y Europa?",
        "answer":"Júpiter"
    },
    {
        "question": "Con qué denominación se conoce la línea dibujada por las estrellas Alnitak, Alnilam y Mintaka vistas desde nuestro planeta?",
        "answer":"Cinturón de Orión"
    },
    {
        "question": "Cuándo se celebró la primera Copa Mundial de Fútbol?",
        "answer":"1930"
    },
    {
        "question": "Como se llamaba la mascota de las Juegos Olímpicos de 1992, los cuales se celebraron en Barcelona?",
        "answer":"Cobi"
    },
    {
        "question": "Qué periodista deportivo popularizó la expresión 'Jugón' para referirse a cracks tanto del fútbol como del baloncesto?",
        "answer":"Andrés Montes"
    },
    {
        "question": "En qué año llegó el hombre a la Luna?",
        "answer":"1969"
    },
    {
        "question": "De qué país se independizó Eslovenia?",
        "answer":"Yugoslavia"
    },
    {
        "question": "Quién era el emperador de Roma cuando murió Jesús de Nazaret?",
        "answer":"Tiberio"
    },
    {
        "question": "Cuál es la capital de Filipinas?",
        "answer":"Manila"
    },
    {
        "question": "En qué país se encuentra el río Po?",
        "answer":"Italia"
    }
]